Metadata-Version: 1.2
Name: Cuckoo-node
Version: 0.1.0
Summary: Cuckoo sample detonation node
Home-page: https://cuckoosandbox.org/
Author: Stichting Cuckoo Foundation
Author-email: info@hatching.io
License: GPLv3
Platform: UNKNOWN
Classifier: Development Status :: 5 - Production/Stable
Classifier: Intended Audience :: Information Technology
Classifier: Intended Audience :: Science/Research
Classifier: Natural Language :: English
Classifier: License :: OSI Approved :: GNU General Public License v3 (GPLv3)
Classifier: Operating System :: POSIX :: Linux
Classifier: Programming Language :: Python :: 3.6
Classifier: Programming Language :: Python :: 3.7
Classifier: Programming Language :: Python :: 3.8
Classifier: Topic :: Security
Requires-Python: >=3.6
